mcp_server_bwt/__init__.py
mcp_server_bwt/__main__.py
mcp_server_bwt/main.py
mcp_server_bwt/version.py
iflow_mcp_isiahw1_mcp_server_bing_webmaster-1.0.0.dist-info/METADATA
iflow_mcp_isiahw1_mcp_server_bing_webmaster-1.0.0.dist-info/WHEEL
iflow_mcp_isiahw1_mcp_server_bing_webmaster-1.0.0.dist-info/entry_points.txt
iflow_mcp_isiahw1_mcp_server_bing_webmaster-1.0.0.dist-info/licenses/LICENSE
iflow_mcp_isiahw1_mcp_server_bing_webmaster-1.0.0.dist-info/RECORD
