Metadata-Version: 2.4
Name: iflow-mcp_isiahw1_mcp-server-bing-webmaster
Version: 1.0.0
Summary: MCP server for Bing Webmaster Tools integration
Project-URL: Homepage, https://github.com/isiahw1/mcp-server-bing-webmaster
Project-URL: Bug Tracker, https://github.com/isiahw1/mcp-server-bing-webmaster/issues
Project-URL: Documentation, https://github.com/isiahw1/mcp-server-bing-webmaster#readme
Author-email: Isiah Wheeler <github@isiahwheeler.com>
License-File: LICENSE
Keywords: api,bing,mcp,seo,webmaster
Classifier: Development Status :: 4 - Beta
Classifier: Intended Audience :: Developers
Classifier: License :: OSI Approved :: MIT License
Classifier: Operating System :: OS Independent
Classifier: Programming Language :: Python :: 3
Classifier: Programming Language :: Python :: 3.10
Classifier: Programming Language :: Python :: 3.11
Classifier: Programming Language :: Python :: 3.12
Classifier: Programming Language :: Python :: 3.13
Classifier: Topic :: Internet :: WWW/HTTP
Classifier: Topic :: Software Development :: Libraries
Requires-Python: >=3.10
Requires-Dist: httpx>=0.28.0
Requires-Dist: mcp[cli]>=1.10.0
Requires-Dist: python-dotenv>=1.0.0
